done2334/__init__.py
done2334/done2334.py
done2334-1.0.dist-info/METADATA
done2334-1.0.dist-info/WHEEL
done2334-1.0.dist-info/top_level.txt
done2334-1.0.dist-info/RECORD
