Metadata-Version: 2.4
Name: done2334
Version: 1.0
Summary: This is just a test package
Author: Noman
Author-email: mnomanansari99@gmail.com
Requires-Python: >=3.6
Dynamic: author
Dynamic: author-email
Dynamic: requires-python
Dynamic: summary
